bluemastodon/__init__.py
bluemastodon/__main__.py
bluemastodon/bluesky.py
bluemastodon/config.py
bluemastodon/mastodon.py
bluemastodon/models.py
bluemastodon/sync.py
bluemastodon-0.9.7.dist-info/LICENSE
bluemastodon-0.9.7.dist-info/METADATA
bluemastodon-0.9.7.dist-info/WHEEL
bluemastodon-0.9.7.dist-info/entry_points.txt
bluemastodon-0.9.7.dist-info/RECORD
