Metadata-Version: 2.1
Name: bluemastodon
Version: 0.9.7
Summary: A tool to synchronize posts from Bluesky to Mastodon
Home-page: https://github.com/kelp/bluemastodon
License: MIT
Keywords: bluesky,mastodon,social-media,cross-posting,automation
Author: Travis Cole
Author-email: kelp@plek.org
Requires-Python: >=3.10,<3.14
Classifier: Development Status :: 4 - Beta
Classifier: Environment :: Console
Classifier: Intended Audience :: End Users/Desktop
Classifier: License :: OSI Approved :: MIT License
Classifier: Programming Language :: Python :: 3
Classifier: Programming Language :: Python :: 3.10
Classifier: Programming Language :: Python :: 3.11
Classifier: Programming Language :: Python :: 3.12
Classifier: Programming Language :: Python :: 3.13
Classifier: Topic :: Communications
Classifier: Topic :: Internet
Requires-Dist: atproto (>=0.0.59)
Requires-Dist: loguru (>=0.7.2)
Requires-Dist: mastodon-py[blurhash] (>=1.8.1)
Requires-Dist: pydantic (>=2.6.1)
Requires-Dist: python-dotenv (>=1.0.0)
Project-URL: Bug Tracker, https://github.com/kelp/bluemastodon/issues
Project-URL: Changelog, https://github.com/kelp/bluemastodon/blob/main/CHANGELOG.md
Project-URL: Documentation, https://github.com/kelp/bluemastodon/tree/main/docs
Project-URL: Repository, https://github.com/kelp/bluemastodon
